{
  "generated_at": "2026-04-01 07:53:41 UTC+09:00",
  "date": "2026-04-01",
  "last_trading_day": "2026-04-01",
  "weekend_note": "",
  "news": {
    "politics": [
      {
        "title": "\"석유는 알아서\" 선 긋는 트럼프…네타냐후는 '성과 과시'",
        "url": "https://news.jtbc.co.kr/article/NB12292178?influxDiv=NAVER",
        "src": "news.jtbc.co.kr"
      },
      {
        "title": "네타냐후, 성경 '10대 재앙' 빗대 \"이란에 '5대 재앙' 입혀",
        "url": "https://www.hankookilbo.com/news/article/A2026040107420005409?did=NA",
        "src": "hankookilbo.com"
      },
      {
        "title": "김정관 장관, '비축석유 北유입설' 유튜버 고발",
        "url": "https://biz.sbs.co.kr/article_hub/20000301211?division=NAVER",
        "src": "biz.sbs.co.kr"
      },
      {
        "title": "‘KBS 열린토론’ 신규 진행자로 황현희 발탁...\"이기는 토론이 아닌 이...",
        "url": "https://kstar.kbs.co.kr/list_view.html?idx=397206",
        "src": "kstar.kbs.co.kr"
      },
      {
        "title": "조국 대표, 전북 군산 지역구에 출마할 수 있을까?",
        "url": "http://www.breaknews.com/1196760",
        "src": "breaknews.com"
      },
      {
        "title": "경북 민주당 지선 후보 이야기...'빨간 나라를 보았니' 4월 개봉",
        "url": "https://www.slist.kr/news/articleView.html?idxno=728315",
        "src": "slist.kr"
      },
      {
        "title": "2026_4_1 오늘의 주요뉴스",
        "url": "https://kjmbc.co.kr/NewsArticle/1511971",
        "src": "kjmbc.co.kr"
      },
      {
        "title": "조국혁신당 예비후보들 \"선거제 개선 논의 무산...민주당 결단하라\" 촉...",
        "url": "https://kjmbc.co.kr/NewsArticle/1511974",
        "src": "kjmbc.co.kr"
      },
      {
        "title": "\"민주당 일당 독점 깨뜨릴 것\"...호남 정치 변화 만들어낼까",
        "url": "https://kjmbc.co.kr/NewsArticle/1511973",
        "src": "kjmbc.co.kr"
      }
    ],
    "economy": [
      {
        "title": "고양특례시, 룩셈부르크 국립보건원 유치…정밀의료 글로벌 협력 거점 ...",
        "url": "https://www.newsfreezone.co.kr/news/articleView.html?idxno=682777",
        "src": "newsfreezone.co.kr"
      },
      {
        "title": "포천시 “평화경제특구 최종 지정으로 이어져야 한다”",
        "url": "https://biz.heraldcorp.com/article/10707101?ref=naver",
        "src": "biz.heraldcorp.com"
      },
      {
        "title": "트럼프 \"이란 철수 임박\"…유가 안정 카드 꺼내며 2~3주내 완료 선언",
        "url": "https://www.thefairnews.co.kr/news/articleView.html?idxno=73073",
        "src": "thefairnews.co.kr"
      },
      {
        "title": "[부자들의 투자노트] 프랭클린템플턴 \"분산투자 효과적…中증시 주목해...",
        "url": "https://biz.sbs.co.kr/article_hub/20000301196?division=NAVER",
        "src": "biz.sbs.co.kr"
      },
      {
        "title": "인천경제청-인천창조경제혁신센터 맞손... 'K-바이오랩허브' 구축 본격...",
        "url": "https://ic.newdaily.co.kr/site/data/html/2026/03/31/2026033100491.html",
        "src": "ic.newdaily.co.kr"
      },
      {
        "title": "백주선 더불어민주당 남양시장 예비후보, 산업은행 박상진회장 면담",
        "url": "https://sports.khan.co.kr/article/202604010750003?pt=nv",
        "src": "sports.khan.co.kr"
      },
      {
        "title": "에너지 컨설팅업체 \"유가, 150~200달러까지 간다\"",
        "url": "https://biz.sbs.co.kr/article_hub/20000301212?division=NAVER",
        "src": "biz.sbs.co.kr"
      },
      {
        "title": "[강원관광재단]2026년 ‘오감트레일’ 사업 본격 추진",
        "url": "https://www.sportsseoul.com/news/read/1598785?ref=naver",
        "src": "sportsseoul.com"
      },
      {
        "title": "소진공, 동네슈퍼에 소비자가 990원 '착한 소주' 공급",
        "url": "https://view.asiae.co.kr/article/2026040107495242922",
        "src": "view.asiae.co.kr"
      }
    ],
    "society": [
      {
        "title": "[포토] 구로구, 소상공인 환경정화 봉사활동",
        "url": "http://www.edaily.co.kr/news/newspath.asp?newsid=02899526645411856",
        "src": "edaily.co.kr"
      },
      {
        "title": "“사무실 가면, 얼굴 망가진다”…출근 이후 달라진 ‘외모’ 영상, 직...",
        "url": "https://biz.heraldcorp.com/article/10707102?ref=naver",
        "src": "biz.heraldcorp.com"
      },
      {
        "title": "동작구, 사당동에 '어르신 전용 헬스장'…이용료 하루 500원",
        "url": "https://view.asiae.co.kr/article/2026040107513457650",
        "src": "view.asiae.co.kr"
      },
      {
        "title": "'섬비엔날레 준비 박차·생명존중 교육 확대' 보령, 문화·안전 '동시 강...",
        "url": "https://www.bzeronews.com/news/articleView.html?idxno=815218",
        "src": "bzeronews.com"
      },
      {
        "title": "[강원관광재단]2026년 ‘오감트레일’ 사업 본격 추진",
        "url": "https://www.sportsseoul.com/news/read/1598785?ref=naver",
        "src": "sportsseoul.com"
      },
      {
        "title": "인천 옹진군-영흥우리의원, 협업형 재택의료센터 업무협약",
        "url": "https://ic.newdaily.co.kr/site/data/html/2026/03/31/2026033100490.html",
        "src": "ic.newdaily.co.kr"
      },
      {
        "title": "김정관 장관, '비축석유 北유입설' 유튜버 고발",
        "url": "https://biz.sbs.co.kr/article_hub/20000301211?division=NAVER",
        "src": "biz.sbs.co.kr"
      },
      {
        "title": "‘KBS 열린토론’ 신규 진행자로 황현희 발탁...\"이기는 토론이 아닌 이...",
        "url": "https://kstar.kbs.co.kr/list_view.html?idx=397206",
        "src": "kstar.kbs.co.kr"
      },
      {
        "title": "대한노인회 경기 고양시 덕양구지회, 2026년 노인자원봉사자 필수교육 ...",
        "url": "https://www.100ssd.co.kr/news/articleView.html?idxno=207429",
        "src": "100ssd.co.kr"
      }
    ],
    "culture": [
      {
        "title": "청주시, 4월 축제·공연·체험 행사 풍성…원도심 낮과 밤 모두 즐긴다",
        "url": "https://news.bbsi.co.kr/news/articleView.html?idxno=4075402",
        "src": "news.bbsi.co.kr"
      },
      {
        "title": "[포토] 구로구, 소상공인 환경정화 봉사활동",
        "url": "http://www.edaily.co.kr/news/newspath.asp?newsid=02899526645411856",
        "src": "edaily.co.kr"
      },
      {
        "title": "[1보] 광양시 구봉산 관광단지 진입도로 변경 논란…특혜·유착 의혹 제...",
        "url": "https://daily.hankooki.com/news/articleView.html?idxno=1353790",
        "src": "daily.hankooki.com"
      },
      {
        "title": "봄에 가볼 만한 곳, 철원의 푸른 자연과 역사 속으로",
        "url": "https://www.joongangenews.com/news/articleView.html?idxno=505164",
        "src": "joongangenews.com"
      },
      {
        "title": "[강원관광재단]2026년 ‘오감트레일’ 사업 본격 추진",
        "url": "https://www.sportsseoul.com/news/read/1598785?ref=naver",
        "src": "sportsseoul.com"
      },
      {
        "title": "'섬비엔날레 준비 박차·생명존중 교육 확대' 보령, 문화·안전 '동시 강...",
        "url": "https://www.bzeronews.com/news/articleView.html?idxno=815218",
        "src": "bzeronews.com"
      },
      {
        "title": "앞으로 10월 21일은 ‘한복의 날’…한복진흥법, 국회 통과",
        "url": "https://www.sedaily.com/article/20026720?ref=naver",
        "src": "sedaily.com"
      },
      {
        "title": "‘KBS 열린토론’ 신규 진행자로 황현희 발탁...\"이기는 토론이 아닌 이...",
        "url": "https://kstar.kbs.co.kr/list_view.html?idx=397206",
        "src": "kstar.kbs.co.kr"
      },
      {
        "title": "조국 대표, 전북 군산 지역구에 출마할 수 있을까?",
        "url": "http://www.breaknews.com/1196760",
        "src": "breaknews.com"
      }
    ],
    "world": [
      {
        "title": "[부자들의 투자노트] 프랭클린템플턴 \"분산투자 효과적…中증시 주목해...",
        "url": "https://biz.sbs.co.kr/article_hub/20000301196?division=NAVER",
        "src": "biz.sbs.co.kr"
      },
      {
        "title": "포천시 “평화경제특구 최종 지정으로 이어져야 한다”",
        "url": "https://biz.heraldcorp.com/article/10707101?ref=naver",
        "src": "biz.heraldcorp.com"
      },
      {
        "title": "에너지 컨설팅업체 \"유가, 150~200달러까지 간다\"",
        "url": "https://biz.sbs.co.kr/article_hub/20000301212?division=NAVER",
        "src": "biz.sbs.co.kr"
      },
      {
        "title": "‘영재발굴단 인피니티’ 전민철의 재출연",
        "url": "https://www.bntnews.co.kr/article/view/bnt202604010028",
        "src": "bntnews.co.kr"
      },
      {
        "title": "[공식성명] \"여성 폭력 가해자 지지, 데 제르비 감독 선임 반대한다\"......",
        "url": "https://www.interfootball.co.kr/news/articleView.html?idxno=683301",
        "src": "interfootball.co.kr"
      },
      {
        "title": "봄에 가볼 만한 곳, 철원의 푸른 자연과 역사 속으로",
        "url": "https://www.joongangenews.com/news/articleView.html?idxno=505164",
        "src": "joongangenews.com"
      },
      {
        "title": "'영재발굴단' 전민철 재출연…세계적 발레리노 성장기 조명",
        "url": "https://www.slist.kr/news/articleView.html?idxno=728317",
        "src": "slist.kr"
      },
      {
        "title": "'존 윅' 제작진의 뉴 노멀 액션 영화 '노멀' 메인 포스터 & 메인 예고편...",
        "url": "https://www.stardailynews.co.kr/news/articleView.html?idxno=529910",
        "src": "stardailynews.co.kr"
      },
      {
        "title": "'컨디션·샷감 괜찮은' 박성현, 관건은 경기 감각 회복력 [KLPGA 더 시에나...",
        "url": "https://golfhankook.hankooki.com/news/articleView.html?idxno=20019573",
        "src": "golfhankook.hankooki.com"
      }
    ],
    "technology": [
      {
        "title": "충남도, 2차 공공기관 유치전 본격화",
        "url": "http://www.breaknews.com/1196727",
        "src": "breaknews.com"
      },
      {
        "title": "국회 본회의, 환율안정법·노동절 공휴일 등 70건 전격 통과",
        "url": "http://www.breaknews.com/1196705",
        "src": "breaknews.com"
      },
      {
        "title": "46년 묶인 부산 산업단지 규제 대전환…유치업종 전면 개편으로 미래 산...",
        "url": "http://www.breaknews.com/1196691",
        "src": "breaknews.com"
      },
      {
        "title": "중도 정치노선 인터넷 언론사 ‘굿리더뉴스’ 창간",
        "url": "http://www.breaknews.com/1196429",
        "src": "breaknews.com"
      },
      {
        "title": "카타르 LNG 공급계약 불가항력 선언, 러시아와 관계 개선 절호의 기회",
        "url": "http://www.breaknews.com/1196368",
        "src": "breaknews.com"
      },
      {
        "title": "[6.3 지방선거 특집 인터뷰] 한국형 시민의회 모델 권위자 김상준 교수...",
        "url": "http://www.breaknews.com/1196362",
        "src": "breaknews.com"
      },
      {
        "title": "경기도, ‘제조 AI 솔루션 개발지원센터’ 2차년도 사업 추진",
        "url": "http://www.breaknews.com/1196103",
        "src": "breaknews.com"
      },
      {
        "title": "‘도전보다 안정’ 과기원생, 10명 중 1명만 창업 선택",
        "url": "http://www.breaknews.com/1196019",
        "src": "breaknews.com"
      },
      {
        "title": "이스라엘, 나탄즈 핵 기지 공습-이란, 이스라엘 디모나 원전 보복공습 ...",
        "url": "http://www.breaknews.com/1195932",
        "src": "breaknews.com"
      }
    ],
    "entertainment": [
      {
        "title": "故 박상규, 뇌졸중 투병 중 사망…벌써 13년 [RE:멤버]",
        "url": "https://www.tvreport.co.kr/entertainment/article/1022818/",
        "src": "tvreport.co.kr"
      },
      {
        "title": "김미려, '희소질환' 아들과 행복한 시간 공개",
        "url": "https://www.newsis.com/view/NISX20260401_0003572452",
        "src": "newsis.com"
      },
      {
        "title": "먹방 크리에이터 겸 걸그룹 아나운서 박서휘, 연예인에서 무속인 '월검...",
        "url": "https://www.stardailynews.co.kr/news/articleView.html?idxno=529744",
        "src": "stardailynews.co.kr"
      },
      {
        "title": "\"매일 소주 10병 40년 마셨다\" 가수 박상규, 뇌졸중 투병 중 사망…오늘...",
        "url": "https://www.mydaily.co.kr/page/view/2026040105435325877",
        "src": "mydaily.co.kr"
      },
      {
        "title": "[단독]배우 류화영, 3살 연상 사업가와 결혼",
        "url": "https://star.ytn.co.kr/_sn/0117_202604010743036053",
        "src": "star.ytn.co.kr"
      },
      {
        "title": "장영란만 잘못?… 유튜브 뒷광고는 '불법' 연계편성은 '합법'",
        "url": "https://www.mediatoday.co.kr/news/articleView.html?idxno=333460",
        "src": "mediatoday.co.kr"
      },
      {
        "title": "美ICE 구금시설서 올해만 14명 사망…마돈나도 시설폐쇄 촉구",
        "url": "https://www.yna.co.kr/view/AKR20260401019600075?input=1195m",
        "src": "yna.co.kr"
      },
      {
        "title": "'김승규♥' 김진경, 30주차 러블리 D라인..밀착 셀카 보니[스타이슈]",
        "url": "https://www.starnewskorea.com/star/2026/04/01/2026040107341523607",
        "src": "starnewskorea.com"
      },
      {
        "title": "‘시험관 도전’ 류이서 “남편 아프자 무서웠다”…♥전진 닮은 2세 결...",
        "url": "https://www.mk.co.kr/article/12004495",
        "src": "mk.co.kr"
      }
    ],
    "sports": [
      {
        "title": "[강원관광재단]2026년 ‘오감트레일’ 사업 본격 추진",
        "url": "https://www.sportsseoul.com/news/read/1598785?ref=naver",
        "src": "sportsseoul.com"
      },
      {
        "title": "먹방 크리에이터 겸 걸그룹 아나운서 박서휘, 연예인에서 무속인 '월검...",
        "url": "https://www.stardailynews.co.kr/news/articleView.html?idxno=529744",
        "src": "stardailynews.co.kr"
      },
      {
        "title": "엔플라잉, '플래시백' 역주행 열기 잇는다…스페셜 클립 공개→'뮤직뱅...",
        "url": "http://www.stoo.com/article.php?aid=105856329137",
        "src": "stoo.com"
      },
      {
        "title": "[강원관광재단]원주·영월 ｢오감자 페스타｣ 본격 운영",
        "url": "https://www.sportsseoul.com/news/read/1598783?ref=naver",
        "src": "sportsseoul.com"
      },
      {
        "title": "홍명보호에 패한 가나 대표팀 아도 감독, 월드컵 개막 72일 앞두고 경질...",
        "url": "https://sports.donga.com/sports/article/all/20260401/133648569/1",
        "src": "sports.donga.com"
      },
      {
        "title": "삼성전자, 'OLED 풋볼 챔피언십' 개최",
        "url": "http://www.inews24.com/view/1955592",
        "src": "inews24.com"
      },
      {
        "title": "폰세, 5년만의 ML복귀전이 악몽으로…ACL 염좌, 장기 결장 불가피",
        "url": "https://www.sportsseoul.com/news/read/1598781?ref=naver",
        "src": "sportsseoul.com"
      },
      {
        "title": "농어촌생활 만족도 “환경‧경관 높고, 교육 낮아”",
        "url": "https://www.newsam.co.kr/news/article.html?no=42479",
        "src": "newsam.co.kr"
      },
      {
        "title": "'아주리 군단' 이탈리아, 월드컵 본선행 또 좌절",
        "url": "https://www.joongang.co.kr/article/25416588",
        "src": "joongang.co.kr"
      }
    ]
  },
  "limit_up": [],
  "sectors": {
    "이차전지": [
      "삼성SDI",
      "LG에너지솔루션",
      "포스코퓨처엠",
      "에코프로비엠",
      "엘앤에프"
    ],
    "IT": [
      "삼성전자",
      "SK하이닉스",
      "삼성전기",
      "LG전자",
      "네이버"
    ],
    "로봇": [
      "레인보우로보틱스",
      "두산로보틱스",
      "로보스타",
      "유진로봇",
      "에브리봇"
    ],
    "스마트": [
      "LS ELECTRIC",
      "포스코DX",
      "현대오토에버",
      "삼성SDS",
      "LG전자"
    ],
    "AI챗봇": [
      "네이버",
      "카카오",
      "솔트룩스",
      "코난테크놀로지",
      "마인즈랩"
    ],
    "메타버스": [
      "위지윅스튜디오",
      "자이언트스텝",
      "덱스터",
      "넵튠",
      "한빛소프트"
    ],
    "증강현실": [
      "맥스트",
      "와이제이엠게임즈",
      "자이언트스텝",
      "덱스터",
      "한빛소프트"
    ],
    "드론관련": [
      "한화에어로스페이스",
      "LIG넥스원",
      "대한항공",
      "현대로템",
      "퍼스텍"
    ]
  },
  "sector_order": [
    "이차전지",
    "IT",
    "로봇",
    "스마트",
    "AI챗봇",
    "메타버스",
    "증강현실",
    "드론관련"
  ]
}