{
  "generated_at": "2026-02-20 07:54:47 UTC+09:00",
  "date": "2026-02-20",
  "last_trading_day": "2026-02-20",
  "weekend_note": "",
  "news": {
    "politics": [
      {
        "title": "한반도의 운명을 품은 섬, 강화도의 새로운 명소를 찾아서...",
        "url": "http://www.joongang.tv/news/articleView.html?idxno=202267",
        "src": "joongang.tv"
      },
      {
        "title": "이재명 \"지역 균형 발전, 한다면 합니다!\"",
        "url": "https://www.goodmorningcc.com/news/articleView.html?idxno=441325",
        "src": "goodmorningcc.com"
      },
      {
        "title": "[뉴스초점] '내란 우두머리' 尹 1심 무기징역…내란죄 인정",
        "url": "http://www.yonhapnewstv.co.kr/MYH20260220075151ybc",
        "src": "yonhapnewstv.co.kr"
      },
      {
        "title": "이 대통령, 김형석 독립기념관장 해임제청안 재가",
        "url": "http://www.mbn.co.kr/pages/news/newsView.php?news_seq_no=5176718",
        "src": "mbn.co.kr"
      },
      {
        "title": "김지호 민주당 대변인 성남시장 출사표 \"李 대통령 철학, 시정에 접목\"",
        "url": "http://www.edaily.co.kr/news/newspath.asp?newsid=02578086645352488",
        "src": "edaily.co.kr"
      },
      {
        "title": "'북한 최대 정치행사' 9차 당대회 어제 개막",
        "url": "http://www.yonhapnewstv.co.kr/MYH20260220075032IZe",
        "src": "yonhapnewstv.co.kr"
      },
      {
        "title": "12·3 계엄 443일 만의 단죄…법원, 윤석열 '무기징역' 선고",
        "url": "https://news.jtbc.co.kr/article/NB12286086?influxDiv=NAVER",
        "src": "news.jtbc.co.kr"
      },
      {
        "title": "'뉴라이트 논란' 김형석 관장 결국 해임…李 대통령 재가로 마무리",
        "url": "https://www.imaeil.com/page/view/2026022007202158825",
        "src": "imaeil.com"
      },
      {
        "title": "北, ‘최대 정치행사’ 노동당 제9차 대회 19일 개막…김정은 “중장기...",
        "url": "https://www.kukinews.com/article/view/kuk202602200007",
        "src": "kukinews.com"
      }
    ],
    "economy": [
      {
        "title": "[톡톡뉴스] \"청주시 사다리·전동드릴 등 60여종 무상 대여합니다\"",
        "url": "http://www.ttlnews.com/news/articleView.html?idxno=3081479",
        "src": "ttlnews.com"
      },
      {
        "title": "“영국, 美 이란 공습에 자국군 기지 사용 불허”",
        "url": "https://biz.heraldcorp.com/article/10678751?ref=naver",
        "src": "biz.heraldcorp.com"
      },
      {
        "title": "근로소득세, 2020년 40조9천억원→2025년 68조4천억원으로↑",
        "url": "https://www.taxtimes.co.kr/news/article.html?no=273891",
        "src": "taxtimes.co.kr"
      },
      {
        "title": "\"헬로키티와 달콤한 봄맞이 즐겨요\" 롯데호텔 월드, '헬로키티 스트로베...",
        "url": "https://www.ajunews.com/view/20260220074644990",
        "src": "ajunews.com"
      },
      {
        "title": "영등포구, '희망온돌 겨울나기' 성금 30억6000만원…역대 최대",
        "url": "https://view.asiae.co.kr/article/2026022007523246128",
        "src": "view.asiae.co.kr"
      },
      {
        "title": "[금값 시세] 금 5600달러 후 급락… 포지션 정리인가 추세 전환인가",
        "url": "https://www.pinpointnews.co.kr/news/articleView.html?idxno=430684",
        "src": "pinpointnews.co.kr"
      },
      {
        "title": "‘美·이란 전쟁’ 공포감 확산…뉴욕증시, 3대 지수 모두 하락 [투자36...",
        "url": "https://biz.heraldcorp.com/article/10678750?ref=naver",
        "src": "biz.heraldcorp.com"
      },
      {
        "title": "삼성 투자 받은 이스라엘 배터리 스타트업 '스토어닷', 美 나스닥 상장...",
        "url": "https://www.theguru.co.kr/news/article.html?no=98213",
        "src": "theguru.co.kr"
      }
    ],
    "society": [
      {
        "title": "정부, 트럼프 주도 평화위 참석 “가자지구 평화증진 노력 지지”",
        "url": "https://www.chosun.com/politics/diplomacy-defense/2026/02/20/AXG3GVCNNRHW5K33F24U2PVEOI/?utm_source=naver&utm_medium=referral&utm_campaign=naver-news",
        "src": "chosun.com"
      },
      {
        "title": "교육부-노동부, 직업계고 취업지원 유관기관 간담회",
        "url": "https://biz.sbs.co.kr/article_hub/20000292384?division=NAVER",
        "src": "biz.sbs.co.kr"
      },
      {
        "title": "[설탕부담금 논란③] 리터당 최대 300원… 도입되면 내 음료값 얼마나 ...",
        "url": "http://www.newsian.co.kr/news/articleView.html?idxno=86309",
        "src": "newsian.co.kr"
      },
      {
        "title": "경기도, 28개 공공·유관기관 178명 통합채용",
        "url": "http://www.seoulwire.com/news/articleView.html?idxno=707365",
        "src": "seoulwire.com"
      },
      {
        "title": "‘어금니 아빠 사형’ 판사 이성호 “수감자에 보복편지 받아, 퇴근길 ...",
        "url": "https://isplus.com/article/view/isp202602200021",
        "src": "isplus.com"
      },
      {
        "title": "\"유엔은 끝났다\" 트럼프의 가자 평화위원회 출범... 14조원 투입해 '중동...",
        "url": "https://www.g-enews.com/view.php?ud=202602200751073322f4f9a46d5b_1",
        "src": "g-enews.com"
      },
      {
        "title": "영등포구, '희망온돌 겨울나기' 성금 30억6000만원…역대 최대",
        "url": "https://view.asiae.co.kr/article/2026022007523246128",
        "src": "view.asiae.co.kr"
      },
      {
        "title": "'북한 최대 정치행사' 9차 당대회 어제 개막",
        "url": "http://www.yonhapnewstv.co.kr/MYH20260220075032IZe",
        "src": "yonhapnewstv.co.kr"
      },
      {
        "title": "尹측 \"절연 타령 말고 정책 망했으면 후보 내려놔야\"…오세훈 겨냥",
        "url": "https://www.news1.kr/politics/general-politics/6077038",
        "src": "news1.kr"
      }
    ],
    "culture": [
      {
        "title": "[스포츠박사 기자의 스포츠용어 산책 1701] 북한 골프에서 왜 '워터해저...",
        "url": "http://www.maniareport.com/view.php?ud=2026022007493953605e8e941087_19",
        "src": "maniareport.com"
      },
      {
        "title": "경기도, 28개 공공·유관기관 178명 통합채용",
        "url": "http://www.seoulwire.com/news/articleView.html?idxno=707365",
        "src": "seoulwire.com"
      },
      {
        "title": "한반도의 운명을 품은 섬, 강화도의 새로운 명소를 찾아서...",
        "url": "http://www.joongang.tv/news/articleView.html?idxno=202267",
        "src": "joongang.tv"
      },
      {
        "title": "인천시, 삼성·LG와 손잡고 결혼장려문화 확산… 협약 체결",
        "url": "https://ic.newdaily.co.kr/site/data/html/2026/02/19/2026021900480.html",
        "src": "ic.newdaily.co.kr"
      },
      {
        "title": "서울시교육청, '서울SEM119 갈등조정단 봄' 공식 출범",
        "url": "https://www.jeonmae.co.kr/news/articleView.html?idxno=1232008",
        "src": "jeonmae.co.kr"
      },
      {
        "title": "울산시 \"청년문화예술패스 신청하세요\"…19~20세 선착순",
        "url": "https://www.yna.co.kr/view/AKR20260219150200057?input=1195m",
        "src": "yna.co.kr"
      },
      {
        "title": "'감독님 왜 거기 계세요?' 추신수 찬스, 대체 왜 MLB 구단이 연락했을까",
        "url": "https://www.sportschosun.com/baseball/2026-02-19/202602190100122040008422",
        "src": "sportschosun.com"
      },
      {
        "title": "광진구 공약사업 95.7% 이행",
        "url": "https://www.naeil.com/news/read/578536?ref=naver",
        "src": "naeil.com"
      }
    ],
    "world": [
      {
        "title": "피겨 이해인, 여자 싱글 8위로 ‘톱10’...신지아는 11위[밀라노 코르티...",
        "url": "https://www.sedaily.com/article/20010465?ref=naver",
        "src": "sedaily.com"
      },
      {
        "title": "송민영 DGIST 교수팀, 저전력·초소형 디지털 기반 무선 송신기 기술 개...",
        "url": "https://www.etnews.com/20260220000010",
        "src": "etnews.com"
      },
      {
        "title": "‘美·이란 전쟁’ 공포감 확산…뉴욕증시, 3대 지수 모두 하락 [투자36...",
        "url": "https://biz.heraldcorp.com/article/10678750?ref=naver",
        "src": "biz.heraldcorp.com"
      },
      {
        "title": "뉴욕증시, 미국 이란 공습 불안...하락 마감",
        "url": "http://www.issuenbiz.com/news/articleView.html?idxno=73159",
        "src": "issuenbiz.com"
      },
      {
        "title": "한반도의 운명을 품은 섬, 강화도의 새로운 명소를 찾아서...",
        "url": "http://www.joongang.tv/news/articleView.html?idxno=202267",
        "src": "joongang.tv"
      },
      {
        "title": "한국, 전고체전지 분야 특허출원 증가율 세계 2위",
        "url": "https://www.todayenergy.kr/news/articleView.html?idxno=294410",
        "src": "todayenergy.kr"
      },
      {
        "title": "젠슨 황 \"GTC 2026서 세상 못 본 칩 여러 개 꺼낸다\"…삼성·SK하이닉스 ...",
        "url": "https://www.g-enews.com/view.php?ud=202602200717314727fbbec65dfb_1",
        "src": "g-enews.com"
      },
      {
        "title": "이 대통령, 김형석 독립기념관장 해임제청안 재가",
        "url": "http://www.mbn.co.kr/pages/news/newsView.php?news_seq_no=5176718",
        "src": "mbn.co.kr"
      },
      {
        "title": "\"유엔은 끝났다\" 트럼프의 가자 평화위원회 출범... 14조원 투입해 '중동...",
        "url": "https://www.g-enews.com/view.php?ud=202602200751073322f4f9a46d5b_1",
        "src": "g-enews.com"
      }
    ],
    "technology": [
      {
        "title": "[인터뷰] 주호영 “지금 대구에 필요한 건 돌파형 정치가”",
        "url": "http://www.breaknews.com/1185992",
        "src": "breaknews.com"
      },
      {
        "title": "국민의힘, “현 정부 '부동산 독재'&'사법 파괴' 멈춰라… 민생 파탄 임...",
        "url": "http://www.breaknews.com/1185969",
        "src": "breaknews.com"
      },
      {
        "title": "4대 과기원 의·치대행 자퇴 ‘반 토막’…이공계 기류 변화 신호탄 되...",
        "url": "http://www.breaknews.com/1185958",
        "src": "breaknews.com"
      },
      {
        "title": "충남도 산림자원연구소, 고당도 밤 신품종 3종 현장 보급",
        "url": "http://www.breaknews.com/1185953",
        "src": "breaknews.com"
      },
      {
        "title": "대전관광공사, 대전·세종 관광 일자리 지원사업 본격화",
        "url": "http://www.breaknews.com/1185956",
        "src": "breaknews.com"
      },
      {
        "title": "전남해양수산과학원, ‘미래 어촌 리더’ 2026년 수산업경영인 모집",
        "url": "http://www.breaknews.com/1185793",
        "src": "breaknews.com"
      },
      {
        "title": "엔닷라이트, 피지컬 AI 모델 학습용 3D 생성 기술 개발 과제 참여",
        "url": "https://www.venturesquare.net/1039082/",
        "src": "venturesquare.net"
      },
      {
        "title": "제2차 세계대전 당시, 소련에 제공한 미국의 랜드리스(Lend-Lease) 문제에...",
        "url": "http://www.breaknews.com/1185717",
        "src": "breaknews.com"
      },
      {
        "title": "스마트푸드네트웍스, 2026년 데이터바우처 공급기업 선정",
        "url": "https://www.venturesquare.net/1038775/",
        "src": "venturesquare.net"
      }
    ],
    "entertainment": [
      {
        "title": "‘어금니 아빠 사형’ 판사 이성호 “수감자에 보복편지 받아, 퇴근길 ...",
        "url": "https://isplus.com/article/view/isp202602200021",
        "src": "isplus.com"
      },
      {
        "title": "'57세' 윤유선, 18살 연하 배우와 핑크빛♥…\"베드신 있으면 감사해야지...",
        "url": "https://www.tenasia.co.kr/article/2026022026234",
        "src": "tenasia.co.kr"
      },
      {
        "title": "윤유선♥이성호, 마라맛 티키타카로 천생연분 인증..부부 첫 동반 토크...",
        "url": "https://www.stardailynews.co.kr/news/articleView.html?idxno=524636",
        "src": "stardailynews.co.kr"
      },
      {
        "title": "‘옥문아’ 윤유선 부부, 시청률 1위",
        "url": "https://www.bntnews.co.kr/article/view/bnt202602200024",
        "src": "bntnews.co.kr"
      },
      {
        "title": "윤유선♥이성호, \"가장 소중한 사람은 내 아내\"…마라맛 공방 끝 훈훈한...",
        "url": "https://www.topstarnews.net/news/articleView.html?idxno=15977938",
        "src": "topstarnews.net"
      },
      {
        "title": "‘윤유선♥’ 판사 남편 “수감자의 보복편지, 퇴근길 오싹…” (옥문아...",
        "url": "https://sports.donga.com/ent/article/all/20260220/133385900/1",
        "src": "sports.donga.com"
      },
      {
        "title": "‘건물주’ 하정우, 종각 95억·방이동 170억 빌딩 2채 매각 추진",
        "url": "https://www.sportsseoul.com/news/read/1587172?ref=naver",
        "src": "sportsseoul.com"
      },
      {
        "title": "'정우성→김용건' 연예계 혼외자 전성시대…가십 너머의 '책임'을 묻다...",
        "url": "https://www.tvreport.co.kr/repot/article/1002632/",
        "src": "tvreport.co.kr"
      },
      {
        "title": "윤유선 판사 남편 이성호 \"어금니 아빠 사건 판결문 탓에 세일러문 별명...",
        "url": "http://enews.imbc.com/News/RetrieveNewsInfo/495244",
        "src": "enews.imbc.com"
      }
    ],
    "sports": [
      {
        "title": "[스포츠박사 기자의 스포츠용어 산책 1701] 북한 골프에서 왜 '워터해저...",
        "url": "http://www.maniareport.com/view.php?ud=2026022007493953605e8e941087_19",
        "src": "maniareport.com"
      },
      {
        "title": "2026 WBC 최고의 선발투수는?→‘미국의 ’스쿠발-스킨스 TOP2‘",
        "url": "https://sports.donga.com/sports/article/all/20260220/133385924/1",
        "src": "sports.donga.com"
      },
      {
        "title": "세븐틴, 싱가포르도 접수…특별한 팬 이벤트",
        "url": "http://www.stoo.com/article.php?aid=105242926345",
        "src": "stoo.com"
      },
      {
        "title": "용인시, 중소기업 7곳 기숙사 임차비...10개월간 총 3300만 원 지원",
        "url": "https://www.sportsseoul.com/news/read/1587174?ref=naver",
        "src": "sportsseoul.com"
      },
      {
        "title": "\"365 생활체육 환경 만든다\"…관악구 체육진흥계획 시행",
        "url": "https://www.yna.co.kr/view/AKR20260220019900004?input=1195m",
        "src": "yna.co.kr"
      },
      {
        "title": "WBC 출전하는 타자 파워 랭킹 1위 오타니…투수 1위는 스쿠벌",
        "url": "https://www.yna.co.kr/view/AKR20260220019800007?input=1195m",
        "src": "yna.co.kr"
      },
      {
        "title": "관악구, 구민 건강과 행복 높이는 체육 복지 실현",
        "url": "https://biz.heraldcorp.com/article/10678745?ref=naver",
        "src": "biz.heraldcorp.com"
      },
      {
        "title": "이재명 대통령 \"원윤종 IOC 선수위원 선출 환영…\"스포츠로 평화·연대 ...",
        "url": "https://www.stnsports.co.kr/news/articleView.html?idxno=312616",
        "src": "stnsports.co.kr"
      },
      {
        "title": "김승수 의원, 지역 e스포츠 대회 과세특례 연장법 대표 발의",
        "url": "https://www.inven.co.kr/webzine/news/?news=313740",
        "src": "inven.co.kr"
      }
    ]
  },
  "limit_up": [],
  "sectors": {
    "이차전지": [
      "삼성SDI",
      "LG에너지솔루션",
      "포스코퓨처엠",
      "에코프로비엠",
      "엘앤에프"
    ],
    "IT": [
      "삼성전자",
      "SK하이닉스",
      "삼성전기",
      "LG전자",
      "네이버"
    ],
    "로봇": [
      "레인보우로보틱스",
      "두산로보틱스",
      "로보스타",
      "유진로봇",
      "에브리봇"
    ],
    "스마트": [
      "LS ELECTRIC",
      "포스코DX",
      "현대오토에버",
      "삼성SDS",
      "LG전자"
    ],
    "AI챗봇": [
      "네이버",
      "카카오",
      "솔트룩스",
      "코난테크놀로지",
      "마인즈랩"
    ],
    "메타버스": [
      "위지윅스튜디오",
      "자이언트스텝",
      "덱스터",
      "넵튠",
      "한빛소프트"
    ],
    "증강현실": [
      "맥스트",
      "와이제이엠게임즈",
      "자이언트스텝",
      "덱스터",
      "한빛소프트"
    ],
    "드론관련": [
      "한화에어로스페이스",
      "LIG넥스원",
      "대한항공",
      "현대로템",
      "퍼스텍"
    ]
  },
  "sector_order": [
    "이차전지",
    "IT",
    "로봇",
    "스마트",
    "AI챗봇",
    "메타버스",
    "증강현실",
    "드론관련"
  ]
}