{
  "generated_at": "2025-11-12 07:43:44 UTC+09:00",
  "date": "2025-11-12",
  "last_trading_day": "2025-11-12",
  "weekend_note": "",
  "news": {
    "politics": [
      {
        "title": "[충청브리핑] ‘골프·식사 접대’ 모두 들여다본다… 경찰, ‘윤건영 ...",
        "url": "https://cc.newdaily.co.kr/site/data/html/2025/11/12/2025111200010.html",
        "src": "cc.newdaily.co.kr"
      },
      {
        "title": "국힘 인천시당 아카데미 학교, '새로운 리더 정치' 강의",
        "url": "https://www.g-enews.com/view.php?ud=2025111207123966549ae5042aca_1",
        "src": "g-enews.com"
      },
      {
        "title": "계엄 알고도 침묵...조태용 前 국장원장 구속",
        "url": "https://www.hankyung.com/article/202511128134i",
        "src": "hankyung.com"
      },
      {
        "title": "[현장 리포트] ① \"조용하지만 뜨겁다\"… 연말 금융권, 신한·우리·BNK ...",
        "url": "https://www.newswhoplus.com/news/articleView.html?idxno=45686",
        "src": "newswhoplus.com"
      },
      {
        "title": "[홍대스트리트북스] 우리는 누구나 소수자가 될 수 있다",
        "url": "https://www.mydaily.co.kr/page/view/2025111207392572808",
        "src": "mydaily.co.kr"
      },
      {
        "title": "[초점] 트럼프 ‘2000달러 관세 배당’ 구상...전문가들 “정치적 발언...",
        "url": "https://www.g-enews.com/view.php?ud=2025111207241213403bc914ac71_1",
        "src": "g-enews.com"
      },
      {
        "title": "【오늘의 법조】 2025년 11월 12일",
        "url": "https://www.lawtimes.co.kr/news/213066",
        "src": "lawtimes.co.kr"
      },
      {
        "title": "[금값 시세] 달러의 종말 신호탄?… \"금값 1온스 1만달러 시대 온다\"",
        "url": "https://www.pinpointnews.co.kr/news/articleView.html?idxno=394604",
        "src": "pinpointnews.co.kr"
      },
      {
        "title": "【오늘의 국회일정】 2025년 11월 12일",
        "url": "https://www.lawtimes.co.kr/news/213067",
        "src": "lawtimes.co.kr"
      }
    ],
    "economy": [
      {
        "title": "[충청브리핑] ‘골프·식사 접대’ 모두 들여다본다… 경찰, ‘윤건영 ...",
        "url": "https://cc.newdaily.co.kr/site/data/html/2025/11/12/2025111200010.html",
        "src": "cc.newdaily.co.kr"
      },
      {
        "title": "전주시-호주 멜버른시, 교류 협력 체결…\"글로벌 영역 확대\"",
        "url": "http://www.hansbiz.co.kr/news/articleView.html?idxno=790646",
        "src": "hansbiz.co.kr"
      },
      {
        "title": "모건스탠리, 하이닉스·삼전 목표가↑",
        "url": "https://www.getnews.co.kr/news/articleView.html?idxno=848696",
        "src": "getnews.co.kr"
      },
      {
        "title": "[초점] 트럼프 ‘2000달러 관세 배당’ 구상...전문가들 “정치적 발언...",
        "url": "https://www.g-enews.com/view.php?ud=2025111207241213403bc914ac71_1",
        "src": "g-enews.com"
      },
      {
        "title": "BGF리테일, 노인인력개발원·부동산원과 손잡고 ‘시니어 편의점’ 문 ...",
        "url": "https://www.viva100.com/article/20251112500119",
        "src": "viva100.com"
      },
      {
        "title": "김장철엔 주춤, 해외에선 성장…김치 산업 체질 전환",
        "url": "https://www.newsway.co.kr/news/view?ud=2025111116442714731",
        "src": "newsway.co.kr"
      },
      {
        "title": "당진시, 2년 연속 우수 가공상품 비즈니스 모델 경진대회 수상",
        "url": "https://www.joongdo.co.kr/web/view.php?key=20251112010004142",
        "src": "joongdo.co.kr"
      },
      {
        "title": "홈플러스 김병주·김광일 사기혐의, 기소 촉구",
        "url": "http://www.nongaek.com/news/articleView.html?idxno=93206",
        "src": "nongaek.com"
      },
      {
        "title": "【오늘의 국회일정】 2025년 11월 12일",
        "url": "https://www.lawtimes.co.kr/news/213067",
        "src": "lawtimes.co.kr"
      }
    ],
    "society": [
      {
        "title": "[충청브리핑] ‘골프·식사 접대’ 모두 들여다본다… 경찰, ‘윤건영 ...",
        "url": "https://cc.newdaily.co.kr/site/data/html/2025/11/12/2025111200010.html",
        "src": "cc.newdaily.co.kr"
      },
      {
        "title": "코디 폰세… 한국 다음 행선지는?",
        "url": "https://www.bntnews.co.kr/article/view/bnt202511120012",
        "src": "bntnews.co.kr"
      },
      {
        "title": "BGF리테일, 노인인력개발원·부동산원과 손잡고 ‘시니어 편의점’ 문 ...",
        "url": "https://www.viva100.com/article/20251112500119",
        "src": "viva100.com"
      },
      {
        "title": "[홍대스트리트북스] 우리는 누구나 소수자가 될 수 있다",
        "url": "https://www.mydaily.co.kr/page/view/2025111207392572808",
        "src": "mydaily.co.kr"
      },
      {
        "title": "홈플러스 김병주·김광일 사기혐의, 기소 촉구",
        "url": "http://www.nongaek.com/news/articleView.html?idxno=93206",
        "src": "nongaek.com"
      },
      {
        "title": "아산시, '2025 사랑의 김장 나눔' 행사 개최",
        "url": "https://daily.hankooki.com/news/articleView.html?idxno=1294939",
        "src": "daily.hankooki.com"
      },
      {
        "title": "【오늘의 국회일정】 2025년 11월 12일",
        "url": "https://www.lawtimes.co.kr/news/213067",
        "src": "lawtimes.co.kr"
      },
      {
        "title": "\"하얀 얼굴, 까만 얼굴\"...李대통령 \"혐오 표현 묵과 안 돼. 저질 정당 ...",
        "url": "https://www.tjb.co.kr/news05/bodo/view/id/88185",
        "src": "tjb.co.kr"
      },
      {
        "title": "[더벨][한국부동산개발협회 A.N.D 20년]차세대 디벨로퍼 육성 미션, 새 ...",
        "url": "https://www.thebell.co.kr/free/content/ArticleView.asp?key=202511111417200160107968",
        "src": "thebell.co.kr"
      }
    ],
    "culture": [
      {
        "title": "[충청브리핑] ‘골프·식사 접대’ 모두 들여다본다… 경찰, ‘윤건영 ...",
        "url": "https://cc.newdaily.co.kr/site/data/html/2025/11/12/2025111200010.html",
        "src": "cc.newdaily.co.kr"
      },
      {
        "title": "전주시-호주 멜버른시, 교류 협력 체결…\"글로벌 영역 확대\"",
        "url": "http://www.hansbiz.co.kr/news/articleView.html?idxno=790646",
        "src": "hansbiz.co.kr"
      },
      {
        "title": "\"하버드대학 다니고 싶어요\"",
        "url": "https://www.koreadaily.com/article/20251111144209708",
        "src": "koreadaily.com"
      },
      {
        "title": "국힘 인천시당 아카데미 학교, '새로운 리더 정치' 강의",
        "url": "https://www.g-enews.com/view.php?ud=2025111207123966549ae5042aca_1",
        "src": "g-enews.com"
      },
      {
        "title": "코레일유통, ‘서울역에서 만나는 미니어처 유럽여행’ 전시 개최",
        "url": "http://mcnews.co.kr/85256",
        "src": "mcnews.co.kr"
      },
      {
        "title": "[홍대스트리트북스] 우리는 누구나 소수자가 될 수 있다",
        "url": "https://www.mydaily.co.kr/page/view/2025111207392572808",
        "src": "mydaily.co.kr"
      },
      {
        "title": "'한일톱텐쇼' 에녹-마사야 '어른섹시'...박서진-타쿠야 '상남자' 여심저...",
        "url": "https://www.slist.kr/news/articleView.html?idxno=693239",
        "src": "slist.kr"
      },
      {
        "title": "\"집안싸움도 축제\"…마사야·박서진, '한일톱텐쇼' 삼파전 무대→열기 ...",
        "url": "https://www.topstarnews.net/news/articleView.html?idxno=15871901",
        "src": "topstarnews.net"
      },
      {
        "title": "‘도서관과 공연장의 하이브리드’...동작구 ‘까망돌 어울마당 아트홀...",
        "url": "https://biz.heraldcorp.com/article/10614050?ref=naver",
        "src": "biz.heraldcorp.com"
      }
    ],
    "world": [
      {
        "title": "전주시-호주 멜버른시, 교류 협력 체결…\"글로벌 영역 확대\"",
        "url": "http://www.hansbiz.co.kr/news/articleView.html?idxno=790646",
        "src": "hansbiz.co.kr"
      },
      {
        "title": "샤이니 키, 롱샴 팝업 참석…올블랙 수트 룩 ‘시크 매력’ [이주상의 ...",
        "url": "https://www.sportsseoul.com/news/read/1562437?ref=naver",
        "src": "sportsseoul.com"
      },
      {
        "title": "리플 XRP, 비트코인 영향서 벗어나 독자적 안정성 모색",
        "url": "https://www.topstarnews.net/news/articleView.html?idxno=15871902",
        "src": "topstarnews.net"
      },
      {
        "title": "코레일유통, ‘서울역에서 만나는 미니어처 유럽여행’ 전시 개최",
        "url": "http://mcnews.co.kr/85256",
        "src": "mcnews.co.kr"
      },
      {
        "title": "코르티스, 미국 빌보드 9주 연속 차트인",
        "url": "http://www.tvdaily.co.kr/read.php3?aid=17629007351768734010",
        "src": "tvdaily.co.kr"
      },
      {
        "title": "'한일톱텐쇼' 에녹-마사야 '어른섹시'...박서진-타쿠야 '상남자' 여심저...",
        "url": "https://www.slist.kr/news/articleView.html?idxno=693239",
        "src": "slist.kr"
      },
      {
        "title": "오픈AI, 독일 법원서 저작권 침해 판결",
        "url": "https://www.ebn.co.kr/news/articleView.html?idxno=1686325",
        "src": "ebn.co.kr"
      },
      {
        "title": "[금값 시세] 달러의 종말 신호탄?… \"금값 1온스 1만달러 시대 온다\"",
        "url": "https://www.pinpointnews.co.kr/news/articleView.html?idxno=394604",
        "src": "pinpointnews.co.kr"
      },
      {
        "title": "고양시, 31개국 젊은 리더들과 17일 ‘노을빛 고양 한강산책’ 개최",
        "url": "https://www.g-enews.com/view.php?ud=202511112018041970f0f3e23044_1",
        "src": "g-enews.com"
      }
    ],
    "technology": [
      {
        "title": "대전 상장기업 시총 80조 돌파…AI 기업 ‘노타’ 상장으로 상승세 견인",
        "url": "http://www.breaknews.com/1160797",
        "src": "breaknews.com"
      },
      {
        "title": "SKT, ‘1004·1472’ 골드번호 1만개 주인공 찾는다",
        "url": "http://www.breaknews.com/1160232",
        "src": "breaknews.com"
      },
      {
        "title": "김소희 의원 “NDC 졸속 결정...장관 출장 따라 국가전략 종속”",
        "url": "http://www.breaknews.com/1160218",
        "src": "breaknews.com"
      },
      {
        "title": "Reforming the research ecosystem matters more than naming 100 ‘national...",
        "url": "https://koreajoongangdaily.joins.com/news/2025-11-10/englishStudy/bilingualNews/Reforming-the-research-ecosystem-matters-more-than-naming-100-national-scientists-KOR/2440378",
        "src": "koreajoongangdaily.joins.com"
      },
      {
        "title": "태국 현대사의 두 거물들 : 쁠랙 피분 송크람과 프리디 '태국 현대사'",
        "url": "http://www.breaknews.com/1160104",
        "src": "breaknews.com"
      },
      {
        "title": "토종 사운드·AI 팹리스 엑사리온 박우찬 대표 \"사운드 트레이싱 기술력...",
        "url": "http://www.breaknews.com/1160042",
        "src": "breaknews.com"
      },
      {
        "title": "황정아 의원, \"SMR 안전성 강화를 위한 사전검토제 법안 발의\"",
        "url": "http://www.breaknews.com/1159947",
        "src": "breaknews.com"
      },
      {
        "title": "대전시의회 방진영 의원 “과학산업진흥원 용역사업, 세금 낭비로 끝나...",
        "url": "http://www.breaknews.com/1159992",
        "src": "breaknews.com"
      },
      {
        "title": "전남도, 국회 예산심사 총력 대응! 핵심 현안사업 국고 증액 '사활'",
        "url": "http://www.breaknews.com/1160014",
        "src": "breaknews.com"
      }
    ],
    "entertainment": [
      {
        "title": "“마약 때문에 코에 구멍 났다”…마이클잭슨 딸 충격 근황",
        "url": "https://biz.heraldcorp.com/article/10614051?ref=naver",
        "src": "biz.heraldcorp.com"
      },
      {
        "title": "시흥시 '오이도 빨강등대 축제' 개최...갯벌체험부터 버스킹까지",
        "url": "http://www.newsroad.co.kr/news/articleView.html?idxno=48828",
        "src": "newsroad.co.kr"
      },
      {
        "title": "\"긴 여행 시작\"… 송재림 사망 1주기 '향년 39세'",
        "url": "https://www.moneys.co.kr/article/2025111207214487551",
        "src": "moneys.co.kr"
      },
      {
        "title": "①지중해 최고 여행지+②유럽 최고 여행지+③유럽 최고 크루즈 여행지=...",
        "url": "https://sports.khan.co.kr/article/202511120728003?pt=nv",
        "src": "sports.khan.co.kr"
      },
      {
        "title": "“수익 줄었다더니”… 곽튜브, 빠니보틀에 70만원대 샴페인 ‘통 큰 선...",
        "url": "https://isplus.com/article/view/isp202511120004",
        "src": "isplus.com"
      },
      {
        "title": "[시간들] 40년째 어두컴컴…세운상가에 언제쯤 '세계의 기운' 모일까",
        "url": "https://www.yna.co.kr/view/AKR20251111117000546?input=1195m",
        "src": "yna.co.kr"
      },
      {
        "title": "코에 구멍 뚫린 마이클 잭슨 딸…\"얘들아 마약 하지마\" 경고",
        "url": "https://www.joongang.co.kr/article/25381431",
        "src": "joongang.co.kr"
      },
      {
        "title": "[스타트 브리핑] 챗GPT 집단커닝 속출하는데 교육청은 뜬구름 지침",
        "url": "https://www.ytn.co.kr/_ln/0103_202511120706321203",
        "src": "ytn.co.kr"
      },
      {
        "title": "마이클 잭슨 딸 \"마약이 내 인생 망쳐...코에 구멍 뚫렸다\"",
        "url": "https://www.ytn.co.kr/_ln/0104_202511120705085519",
        "src": "ytn.co.kr"
      }
    ],
    "sports": [
      {
        "title": "에버턴, '탈맨유 효과' 노리나… 새 스트라이커 물색 중 지르크지를 주...",
        "url": "https://www.fourfourtwo.co.kr/news/articleView.html?idxno=82588",
        "src": "fourfourtwo.co.kr"
      },
      {
        "title": "전주시-호주 멜버른시, 교류 협력 체결…\"글로벌 영역 확대\"",
        "url": "http://www.hansbiz.co.kr/news/articleView.html?idxno=790646",
        "src": "hansbiz.co.kr"
      },
      {
        "title": "“기대됩니다” 도쿄돔 ‘첫 경험’ 수두룩…‘결전의 장소’ 미리 맛보...",
        "url": "https://www.sportsseoul.com/news/read/1562363?ref=naver",
        "src": "sportsseoul.com"
      },
      {
        "title": "경기도교육청, 교육부 보안감사 ‘최우수기관’ 선정 쾌거",
        "url": "https://www.sportsseoul.com/news/read/1562435?ref=naver",
        "src": "sportsseoul.com"
      },
      {
        "title": "전남교육청, 미국 트로이대학교에서 글로컬 미래역량 강화 연수 운영",
        "url": "http://www.newsmaker.or.kr/news/articleView.html?idxno=171020",
        "src": "newsmaker.or.kr"
      },
      {
        "title": "시흥시 '거북섬 유니버설 광장', 공공가치 디자인 인정...'한국색채대상...",
        "url": "http://www.newsroad.co.kr/news/articleView.html?idxno=48827",
        "src": "newsroad.co.kr"
      },
      {
        "title": "용인도시공사 남사스포츠센터, 청소년수련활동 인증 획득",
        "url": "https://www.startuptoday.co.kr/news/articleView.html?idxno=538909",
        "src": "startuptoday.co.kr"
      },
      {
        "title": "당진시, 도비도-난지도 탄소중립 치유 특구 주민공청회 개최",
        "url": "https://www.joongdo.co.kr/web/view.php?key=20251112010004141",
        "src": "joongdo.co.kr"
      },
      {
        "title": "[신기술] 포바이포 “라이브 스트리밍, 실시간 화질 개선”",
        "url": "https://byline.network/?p=9004111222583468",
        "src": "byline.network"
      }
    ]
  },
  "limit_up": [],
  "sectors": {
    "이차전지": [
      "삼성SDI",
      "LG에너지솔루션",
      "포스코퓨처엠",
      "에코프로비엠",
      "엘앤에프"
    ],
    "IT": [
      "삼성전자",
      "SK하이닉스",
      "삼성전기",
      "LG전자",
      "네이버"
    ],
    "로봇": [
      "레인보우로보틱스",
      "두산로보틱스",
      "로보스타",
      "유진로봇",
      "에브리봇"
    ],
    "스마트": [
      "LS ELECTRIC",
      "포스코DX",
      "현대오토에버",
      "삼성SDS",
      "LG전자"
    ],
    "AI챗봇": [
      "네이버",
      "카카오",
      "솔트룩스",
      "코난테크놀로지",
      "마인즈랩"
    ],
    "메타버스": [
      "위지윅스튜디오",
      "자이언트스텝",
      "덱스터",
      "넵튠",
      "한빛소프트"
    ],
    "증강현실": [
      "맥스트",
      "와이제이엠게임즈",
      "자이언트스텝",
      "덱스터",
      "한빛소프트"
    ],
    "드론관련": [
      "한화에어로스페이스",
      "LIG넥스원",
      "대한항공",
      "현대로템",
      "퍼스텍"
    ]
  },
  "sector_order": [
    "이차전지",
    "IT",
    "로봇",
    "스마트",
    "AI챗봇",
    "메타버스",
    "증강현실",
    "드론관련"
  ]
}